sqmanage/__init__.py
sqmanage/main.py
sqmanage-0.1.0.dist-info/METADATA
sqmanage-0.1.0.dist-info/WHEEL
sqmanage-0.1.0.dist-info/top_level.txt
sqmanage-0.1.0.dist-info/RECORD
