Metadata-Version: 2.1
Name: sqmanage
Version: 0.1.0
Summary: Gestor de sqlite
Author: Josue Santos
Author-email: santosarias502@gmail.com
